{
  "changesets": [
    {
      "releases": [
        {
          "name": "meteor-vite",
          "type": "patch"
        }
      ],
      "summary": "Use the configured Vite client entrypoint as the default entrypoint for Vite dependency optimization. \n\n- Fixes #128",
      "id": "great-melons-eat"
    }
  ],
  "releases": [
    {
      "name": "meteor-vite",
      "type": "patch",
      "oldVersion": "1.10.0",
      "changesets": [
        "great-melons-eat"
      ],
      "newVersion": "1.10.1"
    }
  ]
}